jf_agent/__init__.py
jf_agent/bb_download.py
jf_agent/jira_download.py
jf_agent/main.py
jf_agent-0.0.4.dist-info/LICENSE
jf_agent-0.0.4.dist-info/METADATA
jf_agent-0.0.4.dist-info/WHEEL
jf_agent-0.0.4.dist-info/entry_points.txt
jf_agent-0.0.4.dist-info/top_level.txt
jf_agent-0.0.4.dist-info/RECORD
