Metadata-Version: 2.1
Name: jf-agent
Version: 0.0.4
Summary: An agent for collecting data for jellyfish
Home-page: https://github.com/Jellyfish-AI/jf_agent
License: UNKNOWN
Platform: UNKNOWN
Classifier: Programming Language :: Python :: 3
Classifier: License :: OSI Approved :: MIT License
Classifier: Operating System :: OS Independent
Requires-Dist: jira
Requires-Dist: tqdm
Requires-Dist: stashy
